aadish/__init__.py
aadish/__main__.py
aadish-1.1.4.dist-info/METADATA
aadish-1.1.4.dist-info/WHEEL
aadish-1.1.4.dist-info/entry_points.txt
aadish-1.1.4.dist-info/top_level.txt
aadish-1.1.4.dist-info/RECORD
