Metadata-Version: 2.4
Name: aadish
Version: 1.1.4
Summary: Aadish: An advanced and highly capable AI assistant module.
Home-page: https://pypi.org/project/aadish/
Author: Aadish
Author-email: aadish14146yadav@gmail.com
License: MIT
Classifier: Programming Language :: Python :: 3
Classifier: License :: OSI Approved :: MIT License
Classifier: Operating System :: OS Independent
Requires-Python: >=3.7
Requires-Dist: requests
Requires-Dist: colorama
Requires-Dist: rich
Requires-Dist: pyfiglet
Dynamic: author
Dynamic: author-email
Dynamic: classifier
Dynamic: home-page
Dynamic: license
Dynamic: requires-dist
Dynamic: requires-python
Dynamic: summary
